{
  "replace": false,
  "values": [
    {"id":"supplementaries:sign_post_dark_oak","required":false},
    {"id":"supplementaries:sign_post_oak","required":false},
    {"id":"supplementaries:sign_post_acacia","required":false},
    {"id":"supplementaries:sign_post_jungle","required":false},
    {"id":"supplementaries:sign_post_spruce","required":false},
    {"id":"supplementaries:sign_post_birch","required":false},
    {"id":"supplementaries:sign_post_crimson","required":false},
    {"id":"supplementaries:sign_post_warped","required":false},
    {"id":"supplementaries:sign_post_palm","required":false},
    {"id":"supplementaries:sign_post_mahogany_bop","required":false},
    {"id":"supplementaries:sign_post_sythian","required":false},
    {"id":"supplementaries:sign_post_bulbis","required":false},
    {"id":"supplementaries:sign_post_bamboo","required":false},
    {"id":"supplementaries:sign_post_cika","required":false},
    {"id":"supplementaries:sign_post_charred_lotr","required":false},
    {"id":"supplementaries:sign_post_cypress_lotr","required":false},
    {"id":"supplementaries:sign_post_azure","required":false},
    {"id":"supplementaries:sign_post_rotten_lotr","required":false},
    {"id":"supplementaries:sign_post_rainbow_eucalyptus","required":false},
    {"id":"supplementaries:sign_post_brown_mushroom","required":false},
    {"id":"supplementaries:sign_post_charred_de","required":false},
    {"id":"supplementaries:sign_post_cherrywood","required":false},
    {"id":"supplementaries:sign_post_ebony","required":false},
    {"id":"supplementaries:sign_post_yucca","required":false},
    {"id":"supplementaries:sign_post_maple","required":false},
    {"id":"supplementaries:sign_post_pine_lotr","required":false},
    {"id":"supplementaries:sign_post_aged","required":false},
    {"id":"supplementaries:sign_post_banana_ter","required":false},
    {"id":"supplementaries:sign_post_dream","required":false},
    {"id":"supplementaries:sign_post_runewood","required":false},
    {"id":"supplementaries:sign_post_willow_env","required":false},
    {"id":"supplementaries:sign_post_aspen_lotr","required":false},
    {"id":"supplementaries:sign_post_willow","required":false},
    {"id":"supplementaries:sign_post_sitrus","required":false},
    {"id":"supplementaries:sign_post_glowshroom","required":false},
    {"id":"supplementaries:sign_post_temporal","required":false},
    {"id":"supplementaries:sign_post_cedar_lotr","required":false},
    {"id":"supplementaries:sign_post_mulberry_ter","required":false},
    {"id":"supplementaries:sign_post_twilight_oak_tf","required":false},
    {"id":"supplementaries:sign_post_glowshroom_em","required":false},
    {"id":"supplementaries:sign_post_lucernia","required":false},
    {"id":"supplementaries:sign_post_redwood_bop","required":false},
    {"id":"supplementaries:sign_post_beech_lotr","required":false},
    {"id":"supplementaries:sign_post_morado","required":false},
    {"id":"supplementaries:sign_post_maple_aut","required":false},
    {"id":"supplementaries:sign_post_apple_te","required":false},
    {"id":"supplementaries:sign_post_cherry_bop","required":false},
    {"id":"supplementaries:sign_post_lament","required":false},
    {"id":"supplementaries:sign_post_twisted","required":false},
    {"id":"supplementaries:sign_post_umbran_bop","required":false},
    {"id":"supplementaries:sign_post_mossy_glowshroom","required":false},
    {"id":"supplementaries:sign_post_inverted","required":false},
    {"id":"supplementaries:sign_post_witch_hazel","required":false},
    {"id":"supplementaries:sign_post_plum_ter","required":false},
    {"id":"supplementaries:sign_post_lacugrove","required":false},
    {"id":"supplementaries:sign_post_trans_tf","required":false},
    {"id":"supplementaries:sign_post_imparius","required":false},
    {"id":"supplementaries:sign_post_coconut_ter","required":false},
    {"id":"supplementaries:sign_post_hellbark_bop","required":false},
    {"id":"supplementaries:sign_post_nightshade","required":false},
    {"id":"supplementaries:sign_post_palm_atum","required":false},
    {"id":"supplementaries:sign_post_kousa","required":false},
    {"id":"supplementaries:sign_post_holly_lotr","required":false},
    {"id":"supplementaries:sign_post_mango_ter","required":false},
    {"id":"supplementaries:sign_post_hazel_te","required":false},
    {"id":"supplementaries:sign_post_mangrove","required":false},
    {"id":"supplementaries:sign_post_mushroom_em","required":false},
    {"id":"supplementaries:sign_post_shimmerwood","required":false},
    {"id":"supplementaries:sign_post_tiger_pw","required":false},
    {"id":"supplementaries:sign_post_poise","required":false},
    {"id":"supplementaries:sign_post_pythadendron","required":false},
    {"id":"supplementaries:sign_post_tea","required":false},
    {"id":"supplementaries:sign_post_white","required":false},
    {"id":"supplementaries:sign_post_red_mushroom","required":false},
    {"id":"supplementaries:sign_post_fir","required":false},
    {"id":"supplementaries:sign_post_magic_bop","required":false},
    {"id":"supplementaries:sign_post_magic_pw","required":false},
    {"id":"supplementaries:sign_post_pine","required":false},
    {"id":"supplementaries:sign_post_umbrella_tree","required":false},
    {"id":"supplementaries:sign_post_dreamwood","required":false},
    {"id":"supplementaries:sign_post_grimwood","required":false},
    {"id":"supplementaries:sign_post_dragon_tree","required":false},
    {"id":"supplementaries:sign_post_aspen","required":false},
    {"id":"supplementaries:sign_post_apple_ter","required":false},
    {"id":"supplementaries:sign_post_redwood","required":false},
    {"id":"supplementaries:sign_post_dead_bop","required":false},
    {"id":"supplementaries:sign_post_jacaranda_ab","required":false},
    {"id":"supplementaries:sign_post_mahogany","required":false},
    {"id":"supplementaries:sign_post_maple_pw","required":false},
    {"id":"supplementaries:sign_post_beeswax","required":false},
    {"id":"supplementaries:sign_post_holly","required":false},
    {"id":"supplementaries:sign_post_canopy_tf","required":false},
    {"id":"supplementaries:sign_post_painted_acacia","required":false},
    {"id":"supplementaries:sign_post_netherwood","required":false},
    {"id":"supplementaries:sign_post_purple_heart_pw","required":false},
    {"id":"supplementaries:sign_post_fir_bop","required":false},
    {"id":"supplementaries:sign_post_palo_verde","required":false},
    {"id":"supplementaries:sign_post_zelkova","required":false},
    {"id":"supplementaries:sign_post_lebethron_lotr","required":false},
    {"id":"supplementaries:sign_post_mine_tf","required":false},
    {"id":"supplementaries:sign_post_olive","required":false},
    {"id":"supplementaries:sign_post_fir_lotr","required":false},
    {"id":"supplementaries:sign_post_mangrove_un","required":false},
    {"id":"supplementaries:sign_post_cactus","required":false},
    {"id":"supplementaries:sign_post_cypress_bb","required":false},
    {"id":"supplementaries:sign_post_nanab","required":false},
    {"id":"supplementaries:sign_post_grongle","required":false},
    {"id":"supplementaries:sign_post_livingwood","required":false},
    {"id":"supplementaries:sign_post_edelwood","required":false},
    {"id":"supplementaries:sign_post_cypress","required":false},
    {"id":"supplementaries:sign_post_lemon_ter","required":false},
    {"id":"supplementaries:sign_post_smogstem","required":false},
    {"id":"supplementaries:sign_post_jellyshroom","required":false},
    {"id":"supplementaries:sign_post_time_tf","required":false},
    {"id":"supplementaries:sign_post_helix_tree","required":false},
    {"id":"supplementaries:sign_post_sort_tf","required":false},
    {"id":"supplementaries:sign_post_pear_lotr","required":false},
    {"id":"supplementaries:sign_post_jacaranda","required":false},
    {"id":"supplementaries:sign_post_archwood","required":false},
    {"id":"supplementaries:sign_post_willow_pw","required":false},
    {"id":"supplementaries:sign_post_distortic","required":false},
    {"id":"supplementaries:sign_post_embur","required":false},
    {"id":"supplementaries:sign_post_wisteria_env","required":false},
    {"id":"supplementaries:sign_post_cherry_lotr","required":false},
    {"id":"supplementaries:sign_post_enigma","required":false},
    {"id":"supplementaries:sign_post_end_lotus","required":false},
    {"id":"supplementaries:sign_post_blood","required":false},
    {"id":"supplementaries:sign_post_palm_bop","required":false},
    {"id":"supplementaries:sign_post_baobab","required":false},
    {"id":"supplementaries:sign_post_mirk_oak_lotr","required":false},
    {"id":"supplementaries:sign_post_cave_mushroom","required":false},
    {"id":"supplementaries:sign_post_blue_enchanted","required":false},
    {"id":"supplementaries:sign_post_green_enchanted","required":false},
    {"id":"supplementaries:sign_post_tofustem","required":false},
    {"id":"supplementaries:sign_post_pecha","required":false},
    {"id":"supplementaries:sign_post_elder","required":false},
    {"id":"supplementaries:sign_post_cherry_red","required":false},
    {"id":"supplementaries:sign_post_poisonous_mushroom_em","required":false},
    {"id":"supplementaries:sign_post_dark_tf","required":false},
    {"id":"supplementaries:sign_post_willow_bop","required":false},
    {"id":"supplementaries:sign_post_aspen_atm","required":false},
    {"id":"supplementaries:sign_post_cherry_ter","required":false},
    {"id":"supplementaries:sign_post_skyris","required":false},
    {"id":"supplementaries:sign_post_arcane_edelwood","required":false},
    {"id":"supplementaries:sign_post_mysterywood","required":false},
    {"id":"supplementaries:sign_post_peach_ter","required":false},
    {"id":"supplementaries:sign_post_dead","required":false},
    {"id":"supplementaries:sign_post_lairelosse_lotr","required":false},
    {"id":"supplementaries:sign_post_wigglewood","required":false},
    {"id":"supplementaries:sign_post_fairy_ring_mushroom_hbt","required":false},
    {"id":"supplementaries:sign_post_oran","required":false},
    {"id":"supplementaries:sign_post_deadwood_atum","required":false},
    {"id":"supplementaries:sign_post_larch_lotr","required":false},
    {"id":"supplementaries:sign_post_charred","required":false},
    {"id":"supplementaries:sign_post_darkwood","required":false},
    {"id":"supplementaries:sign_post_mangrove_tf","required":false},
    {"id":"supplementaries:sign_post_mallorn_lotr","required":false},
    {"id":"supplementaries:sign_post_pear_ter","required":false},
    {"id":"supplementaries:sign_post_fir_tr","required":false},
    {"id":"supplementaries:sign_post_maple_lotr","required":false},
    {"id":"supplementaries:sign_post_rosewood","required":false},
    {"id":"supplementaries:sign_post_leppa","required":false},
    {"id":"supplementaries:sign_post_driftwood","required":false},
    {"id":"supplementaries:sign_post_apple_lotr","required":false},
    {"id":"supplementaries:sign_post_cherry_env","required":false},
    {"id":"supplementaries:sign_post_ether","required":false},
    {"id":"supplementaries:sign_post_orange_ter","required":false},
    {"id":"supplementaries:sign_post_silverbell_pw","required":false},
    {"id":"supplementaries:sign_post_river","required":false},
    {"id":"supplementaries:sign_post_tenanea","required":false},
    {"id":"supplementaries:sign_post_cherry","required":false},
    {"id":"supplementaries:sign_post_redbud_ab","required":false},
    {"id":"supplementaries:sign_post_jacaranda_bop","required":false},
    {"id":"supplementaries:sign_post_green_oak_lotr","required":false}
  ]
}