{
  "type": "minecraft:crafting_shaped",
      "conditions": [
        {
          "flag": "hanging_sign",
          "type": "supplementaries:flag"
        },
        {
          "modid": "byg",
          "type": "forge:mod_loaded"
        }
      ],

        "group": "hanging_sign",
        "pattern": [
          "010",
          "222",
          "222"
        ],
        "key": {
          "0": {
            "item": "minecraft:iron_nugget"
          },
          "1": {
            "item": "minecraft:stick"
          },
          "2": {
            "item": "byg:mangrove_planks"
          }
        },
        "result": {
          "item": "supplementaries:hanging_sign_mangrove",
          "count": 2
}}