{
  "advancements": [
    {
      "conditions": [
        {
          "flag": "sign_post",
          "type": "supplementaries:flag"
        },
        {
          "modid": "architects_palette",
          "type": "forge:mod_loaded"
        }
      ],
      "advancement": {
        "parent": "minecraft:recipes/root",
        "rewards": {
          "recipes": [
            "supplementaries:sign_post_twisted"
          ]
        },
        "criteria": {
          "has_plank": {
            "trigger": "minecraft:inventory_changed",
            "conditions": {
              "items": [
                {
                  "item": "architects_palette:twisted_planks"
                }
              ]
            }
          },
          "has_the_recipe": {
            "trigger": "minecraft:recipe_unlocked",
            "conditions": {
              "recipe": "supplementaries:sign_post_twisted"
            }
          }
        },
        "requirements": [
          [
            "has_plank",
            "has_the_recipe"
          ]
        ]
      }
    }
  ]
}