{
  "rewards": {
    "recipes": [
      "supplementaries:blackstone_tile_stairs"
    ]
  },
  "criteria": {
    "has_the_recipe": {
      "trigger": "minecraft:recipe_unlocked",
      "conditions": {
        "recipe": "supplementaries:blackstone_tile_stairs"
      }
    },
    "has_blackstone_tile": {
      "trigger": "minecraft:inventory_changed",
      "conditions": {
        "items": [
          {
            "items": [
              "supplementaries:blackstone_tile"
            ]
          }
        ]
      }
    }
  },
  "requirements": [
    [
      "has_blackstone_tile",
      "has_the_recipe",
      "has_blackstone_tile"
    ]
  ],
  "sends_telemetry_event": false
}